{
  "trip": {
    "start_date": "2026-06-06",
    "end_date": "2026-06-14",
    "max_day_hours": 10,
    "avg_speed_kmh": 70,
    "airport": {
      "name": "Keflavik Airport",
      "lat": 63.985,
      "lon": -22.605
    }
  },
  "locations": [
    {
      "name": "Keflavik Airport",
      "type": "transport",
      "is_included": true,
      "is_booking": false,
      "start_booking": null,
      "end_booking": null,
      "est_visit_time": 0.5,
      "lat": 63.985,
      "lon": -22.605,
      "wiki": "Keflavik International Airport",
      "desc": "Your gateway to Iceland. Pick up the rental car here; it is about a 45-minute drive into Reykjavik."
    },
    {
      "name": "NORR Apartment, Reykjavik",
      "type": "accommodation",
      "is_included": true,
      "is_booking": true,
      "start_booking": "2026-06-06",
      "end_booking": "2026-06-10",
      "est_visit_time": 0.25,
      "lat": 64.126938,
      "lon": -21.891507,
      "wiki": "Reykjavik",
      "desc": "Check in to your central base. No sightseeing today - settle in, rest, and grab a relaxed first dinner."
    },
    {
      "name": "Hallgrimskirkja",
      "type": "attraction",
      "is_included": true,
      "is_booking": false,
      "start_booking": null,
      "end_booking": null,
      "est_visit_time": 0.5,
      "lat": 64.141795,
      "lon": -21.92671,
      "wiki": "Hallgrímskirkja",
      "desc": "Iceland's iconic 74 m basalt-column church. Ride the tower lift for the best rooftop view over the colourful city."
    },
    {
      "name": "Sun Voyager",
      "type": "attraction",
      "is_included": true,
      "is_booking": false,
      "start_booking": null,
      "end_booking": null,
      "est_visit_time": 0.25,
      "lat": 64.147607,
      "lon": -21.922262,
      "wiki": "Sun Voyager",
      "desc": "A gleaming steel sculpture of a Viking-style boat by the sea. A symbol of hope and discovery, lovely at low light."
    },
    {
      "name": "Harpa",
      "type": "attraction",
      "is_included": true,
      "is_booking": false,
      "start_booking": null,
      "end_booking": null,
      "est_visit_time": 0.5,
      "lat": 64.150433,
      "lon": -21.932854,
      "wiki": "Harpa (concert hall)",
      "desc": "Striking glass concert hall with a honeycomb facade inspired by basalt. Free to wander inside the shimmering foyer."
    },
    {
      "name": "Tjornin",
      "type": "attraction",
      "is_included": true,
      "is_booking": false,
      "start_booking": null,
      "end_booking": null,
      "est_visit_time": 0.5,
      "lat": 64.144522,
      "lon": -21.942337,
      "wiki": "Tjörnin",
      "day": 1,
      "desc": "The central city pond, full of birdlife and ringed by pretty houses. A calm spot in the middle of downtown."
    },
    {
      "name": "Perlan",
      "type": "attraction",
      "is_included": true,
      "is_booking": false,
      "start_booking": null,
      "end_booking": null,
      "est_visit_time": 1.0,
      "lat": 64.129246,
      "lon": -21.919028,
      "wiki": "Perlan",
      "desc": "Glass-dome museum on water tanks with an ice-cave exhibit and 360 degree viewing deck. Great rainy-day option."
    },
    {
      "name": "Phallological Museum",
      "type": "attraction",
      "is_included": true,
      "is_booking": false,
      "start_booking": null,
      "end_booking": null,
      "est_visit_time": 1.0,
      "lat": 64.148468,
      "lon": -21.93576,
      "wiki": "Icelandic Phallological Museum",
      "desc": "The world's largest collection of mammal phalluses - quirky and unforgettable. A fun only-in-Iceland curiosity."
    },
    {
      "name": "Baejarins Beztu Pylsur",
      "type": "attraction",
      "is_included": true,
      "is_booking": false,
      "start_booking": null,
      "end_booking": null,
      "est_visit_time": 0.25,
      "lat": 64.148156,
      "lon": -21.937839,
      "wiki": "Bæjarins Beztu Pylsur",
      "desc": "Legendary hot-dog stand serving Iceland's favourite snack since 1937. Order 'eina með öllu' - one with everything."
    },
    {
      "name": "Thorufoss",
      "type": "attraction",
      "is_included": true,
      "is_booking": false,
      "start_booking": null,
      "end_booking": null,
      "est_visit_time": 0.5,
      "lat": 64.260842,
      "lon": -21.369973,
      "wiki": "Þórufoss",
      "desc": "A pretty, less-crowded waterfall that featured in Game of Thrones. A nice warm-up stop on the way east."
    },
    {
      "name": "Bruarfoss",
      "type": "attraction",
      "is_included": true,
      "is_booking": false,
      "start_booking": null,
      "end_booking": null,
      "est_visit_time": 0.75,
      "lat": 64.264235,
      "lon": -20.515873,
      "wiki": "Brúarfoss",
      "desc": "Famous for its vivid turquoise-blue cascades. Reached by a riverside walk that keeps the crowds thin."
    },
    {
      "name": "Strokkur",
      "type": "attraction",
      "is_included": true,
      "is_booking": false,
      "start_booking": null,
      "end_booking": null,
      "est_visit_time": 0.5,
      "lat": 64.312696,
      "lon": -20.300773,
      "wiki": "Strokkur",
      "desc": "Iceland's most reliable geyser, erupting 15-20 m every few minutes. Stand upwind and have your camera ready."
    },
    {
      "name": "Gullfoss",
      "type": "attraction",
      "is_included": true,
      "is_booking": false,
      "start_booking": null,
      "end_booking": null,
      "est_visit_time": 0.75,
      "lat": 64.32661,
      "lon": -20.121682,
      "wiki": "Gullfoss",
      "desc": "The thundering 'Golden Falls' drops in two tiers into a rugged canyon. One of Iceland's most powerful waterfalls."
    },
    {
      "name": "Kerid",
      "type": "attraction",
      "is_included": true,
      "is_booking": false,
      "start_booking": null,
      "end_booking": null,
      "est_visit_time": 0.5,
      "lat": 64.041538,
      "lon": -20.886981,
      "wiki": "Kerið",
      "desc": "A 3,000-year-old volcanic crater with a striking red rim and an aquamarine lake. Easy walk around the rim."
    },
    {
      "name": "Secret Lagoon",
      "type": "attraction",
      "is_included": true,
      "is_booking": false,
      "start_booking": null,
      "end_booking": null,
      "est_visit_time": 1.5,
      "lat": 64.137294,
      "lon": -20.309207,
      "wiki": null,
      "desc": "Iceland's oldest natural geothermal pool in Fluðir. A steamy, rustic place to soak after a day of sightseeing."
    },
    {
      "name": "Bridge Between Continents",
      "type": "attraction",
      "is_included": true,
      "is_booking": false,
      "start_booking": null,
      "end_booking": null,
      "est_visit_time": 0.25,
      "lat": 63.866407,
      "lon": -22.676366,
      "wiki": "Bridge between continents",
      "desc": "Walk over a footbridge spanning the rift between the North American and Eurasian plates. A literal step between continents."
    },
    {
      "name": "Gunnuhver",
      "type": "attraction",
      "is_included": true,
      "is_booking": false,
      "start_booking": null,
      "end_booking": null,
      "est_visit_time": 0.5,
      "lat": 63.819445,
      "lon": -22.68418,
      "wiki": "Gunnuhver",
      "desc": "Iceland's largest mud pool, hissing with steam and boiling clay. Named after an angry ghost said to be trapped here."
    },
    {
      "name": "Valahnukur",
      "type": "attraction",
      "is_included": true,
      "is_booking": false,
      "start_booking": null,
      "end_booking": null,
      "est_visit_time": 0.5,
      "lat": 63.81187,
      "lon": -22.716239,
      "wiki": "Reykjanes",
      "desc": "Dramatic sea cliffs pounded by Atlantic waves, with a nearby lighthouse. Wild, windswept and very photogenic."
    },
    {
      "name": "Krysuvikurberg",
      "type": "attraction",
      "is_included": true,
      "is_booking": false,
      "start_booking": null,
      "end_booking": null,
      "est_visit_time": 0.5,
      "lat": 63.835802,
      "lon": -22.10488,
      "wiki": null,
      "desc": "Towering bird cliffs alive with seabirds in summer. A quieter, rugged stretch of coastline."
    },
    {
      "name": "Akrafjall",
      "type": "attraction",
      "is_included": true,
      "is_booking": false,
      "start_booking": null,
      "end_booking": null,
      "est_visit_time": 0.25,
      "lat": 64.327984,
      "lon": -21.98662,
      "wiki": null,
      "domain": 1,
      "day": 0,
      "desc": "A flat-topped mountain with a parking spot and panoramic fjord views. A quick leg-stretch on the drive north."
    },
    {
      "name": "Grabrok Craters",
      "type": "attraction",
      "is_included": true,
      "is_booking": false,
      "start_booking": null,
      "end_booking": null,
      "est_visit_time": 0.5,
      "lat": 64.771448,
      "lon": -21.531239,
      "wiki": "Grábrók",
      "desc": "A young volcanic crater with a short stairway to the rim. Easy 20-minute climb for sweeping lava-field views."
    },
    {
      "name": "Reykholt Viking House",
      "type": "attraction",
      "is_included": true,
      "is_booking": false,
      "start_booking": null,
      "end_booking": null,
      "est_visit_time": 0.5,
      "lat": 64.666126,
      "lon": -21.295256,
      "wiki": "Reykholt",
      "desc": "Historic settlement linked to saga-writer Snorri Sturluson. A glimpse into medieval Icelandic culture."
    },
    {
      "name": "Eldborg Crater",
      "type": "attraction",
      "is_included": true,
      "is_booking": false,
      "start_booking": null,
      "end_booking": null,
      "est_visit_time": 0.25,
      "lat": 64.77386,
      "lon": -22.302155,
      "wiki": null,
      "desc": "A near-perfect ring-shaped scoria crater rising from green lava fields. Striking even seen from the road."
    },
    {
      "name": "Landbrotalaug",
      "type": "attraction",
      "is_included": true,
      "is_booking": false,
      "start_booking": null,
      "end_booking": null,
      "est_visit_time": 1.5,
      "lat": 64.834488,
      "lon": -22.311917,
      "wiki": null,
      "desc": "A tiny wild hot spring just big enough for two. A magical, secluded soak near your apartment."
    },
    {
      "name": "Eidhus Apartments",
      "type": "accommodation",
      "is_included": true,
      "is_booking": true,
      "start_booking": "2026-06-10",
      "end_booking": "2026-06-12",
      "est_visit_time": 0.25,
      "lat": 64.847843,
      "lon": -22.674408,
      "wiki": null,
      "desc": "Your countryside base on the south side of Snaefellsnes for the next two nights."
    },
    {
      "name": "Ytri-Tunga",
      "type": "attraction",
      "is_included": true,
      "is_booking": false,
      "start_booking": null,
      "end_booking": null,
      "est_visit_time": 0.5,
      "lat": 64.804042,
      "lon": -23.080302,
      "wiki": null,
      "desc": "A golden-sand beach that is one of the best places in Iceland to see wild seals. Bring binoculars."
    },
    {
      "name": "Arnarstapi",
      "type": "attraction",
      "is_included": true,
      "is_booking": false,
      "start_booking": null,
      "end_booking": null,
      "est_visit_time": 0.75,
      "lat": 64.767326,
      "lon": -23.616934,
      "wiki": "Arnarstapi",
      "desc": "A fishing hamlet with arches, blowholes and basalt sea cliffs. A scenic coastal trail leads toward Hellnar."
    },
    {
      "name": "Vatnshellir Cave",
      "type": "attraction",
      "is_included": true,
      "is_booking": false,
      "start_booking": null,
      "end_booking": null,
      "est_visit_time": 1.0,
      "lat": 64.748123,
      "lon": -23.817982,
      "wiki": null,
      "desc": "An 8,000-year-old lava tube explored on a guided tour down a spiral staircase. A cool peek underground."
    },
    {
      "name": "Djupalonssandur",
      "type": "attraction",
      "is_included": true,
      "is_booking": false,
      "start_booking": null,
      "end_booking": null,
      "est_visit_time": 0.5,
      "lat": 64.753534,
      "lon": -23.895529,
      "wiki": "Djúpalónssandur",
      "desc": "A black-pebble beach with dramatic rock formations and old lifting stones once used to test fishermen's strength."
    },
    {
      "name": "Fjoruhusio Cafe",
      "type": "attraction",
      "is_included": true,
      "is_booking": false,
      "start_booking": null,
      "end_booking": null,
      "est_visit_time": 0.5,
      "lat": 64.751769,
      "lon": -23.645506,
      "wiki": null,
      "desc": "A cosy seaside cafe in Hellnar famous for its fish soup and view. A perfect mid-loop lunch."
    },
    {
      "name": "Kirkjufell and Kirkjufellsfoss",
      "type": "attraction",
      "is_included": true,
      "is_booking": false,
      "start_booking": null,
      "end_booking": null,
      "est_visit_time": 0.75,
      "lat": 64.922092,
      "lon": -23.285604,
      "wiki": "Kirkjufell",
      "desc": "Iceland's most photographed mountain, an elegant cone beside a tumbling waterfall. Postcard-perfect in any weather."
    },
    {
      "name": "South Coast Panorama",
      "type": "accommodation",
      "is_included": true,
      "is_booking": true,
      "start_booking": "2026-06-12",
      "end_booking": "2026-06-14",
      "est_visit_time": 0.25,
      "lat": 63.7385,
      "lon": -20.103601,
      "wiki": null,
      "desc": "Your new base near Hvolsvollur, well placed for the south-coast sights. Check in after the long drive south."
    },
    {
      "name": "Seljalandsfoss",
      "type": "attraction",
      "is_included": true,
      "is_booking": false,
      "start_booking": null,
      "end_booking": null,
      "est_visit_time": 1.5,
      "lat": 63.615254,
      "lon": -19.993897,
      "wiki": "Seljalandsfoss",
      "desc": "A 60 m waterfall you can walk completely behind. Bring a rain jacket - you will get misted."
    },
    {
      "name": "Gljufrabui",
      "type": "attraction",
      "is_included": true,
      "is_booking": false,
      "start_booking": null,
      "end_booking": null,
      "est_visit_time": 0.5,
      "lat": 63.620769,
      "lon": -19.986496,
      "wiki": "Gljúfrabúi",
      "desc": "A hidden waterfall tucked inside a mossy canyon, reached by wading a small stream. A secret right next to Seljalandsfoss."
    },
    {
      "name": "Lomagnupur",
      "type": "attraction",
      "is_included": true,
      "is_booking": false,
      "start_booking": null,
      "end_booking": null,
      "est_visit_time": 0.25,
      "lat": 63.956503,
      "lon": -17.48838,
      "wiki": null,
      "desc": "A sheer 670 m cliff-mountain rising from the sandar plains. One of the most imposing sights on the Ring Road."
    },
    {
      "name": "Fjadrargljufur",
      "type": "attraction",
      "is_included": true,
      "is_booking": false,
      "start_booking": null,
      "end_booking": null,
      "est_visit_time": 0.75,
      "lat": 63.77043,
      "lon": -18.172132,
      "wiki": "Fjaðrárgljúfur",
      "desc": "A serpentine 100 m-deep canyon with mossy walls and a winding river. A short clifftop trail offers epic views."
    },
    {
      "name": "Systrakaffi",
      "type": "attraction",
      "is_included": true,
      "is_booking": false,
      "start_booking": null,
      "end_booking": null,
      "est_visit_time": 0.5,
      "lat": 63.79038,
      "lon": -18.047497,
      "wiki": null,
      "desc": "A friendly restaurant in Kirkjubaejarklaustur. A good lunch stop roughly halfway on this long day."
    },
    {
      "name": "Skaftafell and Svartifoss",
      "type": "attraction",
      "is_included": true,
      "is_booking": false,
      "start_booking": null,
      "end_booking": null,
      "est_visit_time": 2.0,
      "lat": 64.027366,
      "lon": -16.975004,
      "wiki": "Svartifoss",
      "desc": "A waterfall framed by black basalt columns within Vatnajokull National Park. A scenic 1.5 km hike each way."
    },
    {
      "name": "Svinafellsjokull",
      "type": "attraction",
      "is_included": true,
      "is_booking": false,
      "start_booking": null,
      "end_booking": null,
      "est_visit_time": 0.5,
      "lat": 64.008361,
      "lon": -16.88013,
      "wiki": null,
      "desc": "A crevassed glacier tongue you can view up close from the parking area. Featured in many films."
    },
    {
      "name": "Jokulsarlon",
      "type": "attraction",
      "is_included": true,
      "is_booking": false,
      "start_booking": null,
      "end_booking": null,
      "est_visit_time": 1.5,
      "lat": 64.048157,
      "lon": -16.179954,
      "wiki": "Jökulsárlón",
      "desc": "A glacier lagoon dotted with floating icebergs and seals. Iceland's most surreal and beautiful natural sight."
    },
    {
      "name": "Diamond Beach",
      "type": "attraction",
      "is_included": true,
      "is_booking": false,
      "start_booking": null,
      "end_booking": null,
      "est_visit_time": 1.0,
      "lat": 64.041325,
      "lon": -16.182552,
      "wiki": "Breiðamerkursandur",
      "desc": "Black sand strewn with glittering icebergs washed up from the lagoon. Your eastern turnaround point."
    },
    {
      "name": "Skogafoss",
      "type": "attraction",
      "is_included": true,
      "is_booking": false,
      "start_booking": null,
      "end_booking": null,
      "est_visit_time": 0.75,
      "lat": 63.531874,
      "lon": -19.510593,
      "wiki": "Skógafoss",
      "desc": "A massive 60 m curtain of water with frequent rainbows. Climb the stairs beside it for a top-down view."
    },
    {
      "name": "Kvernufoss",
      "type": "attraction",
      "is_included": true,
      "is_booking": false,
      "start_booking": null,
      "end_booking": null,
      "est_visit_time": 0.5,
      "lat": 63.528685,
      "lon": -19.48051,
      "wiki": "Kvernufoss",
      "desc": "A quieter neighbour of Skogafoss hidden in a green gorge. You can walk behind this one too."
    },
    {
      "name": "Seljavallalaug",
      "type": "attraction",
      "is_included": true,
      "is_booking": false,
      "start_booking": null,
      "end_booking": null,
      "est_visit_time": 1.5,
      "lat": 63.56614,
      "lon": -19.607565,
      "wiki": null,
      "desc": "One of Iceland's oldest swimming pools, tucked into a mountain valley. A rustic, atmospheric warm soak."
    },
    {
      "name": "Eyjafjallajokull Viewpoint",
      "type": "attraction",
      "is_included": true,
      "is_booking": false,
      "start_booking": null,
      "end_booking": null,
      "est_visit_time": 0.25,
      "lat": 63.543063,
      "lon": -19.667732,
      "wiki": "Eyjafjallajökull",
      "desc": "The infamous volcano whose 2010 eruption grounded European flights. Stop to admire the glacier-capped peak."
    },
    {
      "name": "Dyholaey",
      "type": "attraction",
      "is_included": true,
      "is_booking": false,
      "start_booking": null,
      "end_booking": null,
      "est_visit_time": 1.0,
      "lat": 63.398833,
      "lon": -19.126631,
      "wiki": "Dyrhólaey",
      "desc": "A rocky promontory with a giant sea arch and a lighthouse. A prime spot for puffins in summer."
    },
    {
      "name": "Vik and Yoda Cave",
      "type": "attraction",
      "is_included": true,
      "is_booking": false,
      "start_booking": null,
      "end_booking": null,
      "est_visit_time": 1.0,
      "lat": 63.422125,
      "lon": -19.01382,
      "wiki": "Vík í Mýrdal",
      "desc": "The charming southernmost village, near black-sand beaches and the Yoda-shaped Hjorleifshofoi cave. Last stop before heading west."
    }
  ]
}
